LICENSE
README.md
setup.py
lib_agent.egg-info/PKG-INFO
lib_agent.egg-info/SOURCES.txt
lib_agent.egg-info/dependency_links.txt
lib_agent.egg-info/requires.txt
lib_agent.egg-info/top_level.txt
libagent/__init__.py
libagent/formats.py
libagent/server.py
libagent/util.py
libagent/age/__init__.py
libagent/age/client.py
libagent/device/__init__.py
libagent/device/fake_device.py
libagent/device/interface.py
libagent/device/jade.py
libagent/device/keepkey.py
libagent/device/keepkey_defs.py
libagent/device/ledger.py
libagent/device/onlykey.py
libagent/device/onlykey_defs.py
libagent/device/trezor.py
libagent/device/trezor_defs.py
libagent/device/ui.py
libagent/gpg/__init__.py
libagent/gpg/agent.py
libagent/gpg/client.py
libagent/gpg/decode.py
libagent/gpg/encode.py
libagent/gpg/keyring.py
libagent/gpg/protocol.py
libagent/signify/__init__.py
libagent/ssh/__init__.py
libagent/ssh/client.py
libagent/ssh/protocol.py